mac_md_to_html_pasteboard/__main__.py
mac_md_to_html_pasteboard/styles/github.css
mac_md_to_html_pasteboard/styles/style.css
mac_md_to_html_pasteboard-1.0.11.dist-info/LICENSE
mac_md_to_html_pasteboard-1.0.11.dist-info/METADATA
mac_md_to_html_pasteboard-1.0.11.dist-info/WHEEL
mac_md_to_html_pasteboard-1.0.11.dist-info/entry_points.txt
mac_md_to_html_pasteboard-1.0.11.dist-info/top_level.txt
mac_md_to_html_pasteboard-1.0.11.dist-info/RECORD
