Metadata-Version: 2.1
Name: mac-md-to-html-pasteboard
Version: 1.0.11
Summary: reads markdown from stdin and uses pandoc and pyobjc to copy
Home-page: https://github.com/friedenberg/mac-md-to-html-pasteboard
Author: Sasha Friedenberg
Author-email: carley.f253fa96@icantbelieveitsnotgmail.com
License: UNKNOWN
Platform: UNKNOWN
Classifier: Programming Language :: Python :: 3
Classifier: License :: OSI Approved :: MIT License
Classifier: Environment :: MacOS X :: Cocoa
Requires-Python: >=3.7.3
Requires-Dist: bs4
Requires-Dist: pyobjc-core
Requires-Dist: pyobjc-framework-Cocoa
Requires-Dist: pypandoc
